MANIFEST.in
README.rst
requirements.txt
setup.py
lisa/__init__.py
lisa/plugins/__init__.py
lisa/plugins/ChatterBot/__init__.py
lisa/plugins/ChatterBot/chatterbot.json
lisa/plugins/ChatterBot/lang/es/LC_MESSAGES/chatterbot.mo
lisa/plugins/ChatterBot/lang/es/LC_MESSAGES/chatterbot.po
lisa/plugins/ChatterBot/lang/fr/LC_MESSAGES/chatterbot.mo
lisa/plugins/ChatterBot/lang/fr/LC_MESSAGES/chatterbot.po
lisa/plugins/ChatterBot/lang/sv/LC_MESSAGES/chatterbot.mo
lisa/plugins/ChatterBot/lang/sv/LC_MESSAGES/chatterbot.po
lisa/plugins/ChatterBot/lang/tr/LC_MESSAGES/chatterbot.mo
lisa/plugins/ChatterBot/lang/tr/LC_MESSAGES/chatterbot.po
lisa/plugins/ChatterBot/modules/__init__.py
lisa/plugins/ChatterBot/modules/chatterbot.py
lisa/plugins/ChatterBot/test/__init__.py
lisa/plugins/ChatterBot/test/chat_test.py
lisa/plugins/ChatterBot/web/__init__.py
lisa/plugins/ChatterBot/web/api.py
lisa/plugins/ChatterBot/web/models.py
lisa/plugins/ChatterBot/web/tests.py
lisa/plugins/ChatterBot/web/urls.py
lisa/plugins/ChatterBot/web/views.py
lisa_plugin_ChatterBot.egg-info/PKG-INFO
lisa_plugin_ChatterBot.egg-info/SOURCES.txt
lisa_plugin_ChatterBot.egg-info/dependency_links.txt
lisa_plugin_ChatterBot.egg-info/namespace_packages.txt
lisa_plugin_ChatterBot.egg-info/requires.txt
lisa_plugin_ChatterBot.egg-info/top_level.txt